[
 {
  "_id": "02",
  "count": 85979
 },
 {
  "_id": "01",
  "count": 83419
 },
 {
  "_id": "03",
  "count": 79944
 },
 {
  "_id": "00",
  "count": 77131
 },
 {
  "_id": "23",
  "count": 71582
 },
 {
  "_id": "22",
  "count": 67544
 },
 {
  "_id": "04",
  "count": 66568
 },
 {
  "_id": "21",
  "count": 64769
 },
 {
  "_id": "20",
  "count": 62664
 },
 {
  "_id": "19",
  "count": 55673
 },
 {
  "_id": "05",
  "count": 52208
 },
 {
  "_id": "18",
  "count": 45778
 },
 {
  "_id": "06",
  "count": 40042
 },
 {
  "_id": "17",
  "count": 36525
 },
 {
  "_id": "16",
  "count": 29718
 },
 {
  "_id": "07",
  "count": 29511
 },
 {
  "_id": "15",
  "count": 26524
 },
 {
  "_id": "14",
  "count": 22961
 },
 {
  "_id": "08",
  "count": 21524
 },
 {
  "_id": "13",
  "count": 16589
 },
 {
  "_id": "09",
  "count": 16428
 },
 {
  "_id": "10",
  "count": 12907
 },
 {
  "_id": "12",
  "count": 9603
 },
 {
  "_id": "11",
  "count": 7677
 }
]